protoplasm/__init__.py
protoplasm/grpcserver.py
protoplasm/bases/__init__.py
protoplasm/bases/_client.py
protoplasm/bases/_exwrap.py
protoplasm/bases/_methwrap.py
protoplasm/bases/_remotewrap.py
protoplasm/bases/_servicer.py
protoplasm/bases/dataclass_bases.py
protoplasm/bases/grpc_bases.py
protoplasm/casting/__init__.py
protoplasm/casting/casters.py
protoplasm/casting/castutils.py
protoplasm/casting/dictator.py
protoplasm/casting/objectifier.py
protoplasm/casting/dictators/__init__.py
protoplasm/decorators/__init__.py
protoplasm/decorators/apihelpers.py
protoplasm/errors/__init__.py
protoplasm/errors/_api.py
protoplasm/errors/_base.py
protoplasm/loader/__init__.py
protoplasm/plasm/__init__.py
protoplasm/structs/__init__.py
protoplasm/structs/_base.py
protoplasm/structs/_methodtype.py
protoplasm/structs/_reqestsiter.py
protoplasm/structs/_responseiter.py
protoplasm/structs/dataclassbase.py
protoplasm/structs/_ctx/__init__.py
protoplasm/structs/_ctx/_basectx.py
protoplasm/structs/_ctx/_grpcctx.py
protoplasm-5.3.1.dist-info/LICENSE
protoplasm-5.3.1.dist-info/METADATA
protoplasm-5.3.1.dist-info/WHEEL
protoplasm-5.3.1.dist-info/top_level.txt
protoplasm-5.3.1.dist-info/RECORD
