Metadata-Version: 2.1
Name: protoplasm
Version: 5.3.1
Summary: Utilities for working with Protobuf & gRPC in Python.
Author-email: Thordur Matthiasson <thordurm@ccpgames.com>, Daniel Maxson <dmaxson@ccpgames.com>
License: MIT License
Project-URL: Homepage, https://github.com/ccpgames/protoplasm
Project-URL: Documentation, https://github.com/ccpgames/protoplasm/blob/main/README.md
Project-URL: Repository, https://github.com/ccpgames/protoplasm.git
Project-URL: Issues, https://github.com/ccpgames/protoplasm/issues
Project-URL: Changelog, https://github.com/ccpgames/protoplasm/blob/main/CHANGELOG.md
Keywords: protobuf,proto,dataclasses,tools,ccp,utils
Classifier: Development Status :: 5 - Production/Stable
Classifier: License :: OSI Approved :: MIT License
Classifier: Intended Audience :: Developers
Classifier: Programming Language :: Python
Classifier: Programming Language :: Python :: 3
Classifier: Programming Language :: Python :: 3.8
Classifier: Programming Language :: Python :: 3.9
Classifier: Programming Language :: Python :: 3.10
Classifier: Programming Language :: Python :: 3.11
Classifier: Programming Language :: Python :: 3.12
Classifier: Topic :: Software Development
Classifier: Topic :: Software Development :: Libraries
Classifier: Topic :: Software Development :: Libraries :: Python Modules
Classifier: Topic :: Utilities
License-File: LICENSE
Requires-Dist: ccptools<2,>=1.1
Requires-Dist: protobuf==5.27.2
Requires-Dist: grpcio<2,>=1.66.1
Requires-Dist: grpcio-tools<2,>=1.66.1
Requires-Dist: googleapis-common-protos<2,>=1.65
